guipy/__init__.py
guipy/components/__init__.py
guipy/components/_component.py
guipy/components/button.py
guipy/components/menu.py
guipy/components/plot.py
guipy/components/slider.py
guipy/components/switch.py
guipy/components/textbox.py
guipy/manager.py
guipy/utils.py
guipylib-0.3.1.dist-info/LICENSE
guipylib-0.3.1.dist-info/WHEEL
guipylib-0.3.1.dist-info/METADATA
guipylib-0.3.1.dist-info/RECORD
