Metadata-Version: 2.1
Name: guipylib
Version: 0.3.1
Summary: UI library for pygame
Home-page: https://github.com/Zjjc123/guipy
License: MIT
Author: Casey Culbertson, Jason Zhang
Author-email: me@jasonzhang.dev
Requires-Python: >=3.7,<4.0
Classifier: Intended Audience :: Developers
Classifier: License :: OSI Approved :: MIT License
Classifier: Operating System :: OS Independent
Classifier: Programming Language :: Python :: 3
Classifier: Programming Language :: Python :: 3.7
Classifier: Programming Language :: Python :: 3.8
Classifier: Programming Language :: Python :: 3.9
Classifier: Programming Language :: Python :: 3.10
Classifier: Programming Language :: Python :: 3
Classifier: Programming Language :: Python :: 3.7
Classifier: Programming Language :: Python :: 3.8
Classifier: Programming Language :: Python :: 3.9
Classifier: Topic :: Software Development :: Libraries :: Python Modules
Requires-Dist: pygame (>=2.1.2,<3.0.0)
Project-URL: Repository, https://github.com/Zjjc123/guipy
